{
  "clazz" : "org.apache.commons.fileupload.DiskFileItemSerializeTest",
  "methods" : [ {
    "method" : "testAboveThreshold",
    "datacollectorResults" : [ {
      "name" : "de.dagere.kopeme.datacollection.TimeDataCollectorNoGC",
      "chunks" : [ ],
      "results" : [ {
        "value" : 2.10860696876E10,
        "deviation" : 0.016683966957798762,
        "min" : 2.0581813675E10,
        "max" : 2.1775528364E10,
        "warmup" : 0,
        "iterations" : 10,
        "repetitions" : 200000,
        "commit" : null,
        "vmRunConfiguration" : {
          "showStart" : false,
          "executeBeforeClassInMeasurement" : false,
          "redirectToTemp" : false,
          "redirectToNull" : true,
          "useKieker" : false
        },
        "javaVersion" : "1.8.0_312",
        "cpu" : "model name : Intel(R) Core(TM) i7-4770 CPU @ 3.40GHz",
        "memory" : "MemTotal: 16280696 kB",
        "date" : 1667754729034,
        "fulldata" : {
          "fileName" : null,
          "values" : [ {
            "startTime" : 1667754517912,
            "value" : 21775528364
          }, {
            "startTime" : 1667754539688,
            "value" : 21097406350
          }, {
            "startTime" : 1667754560785,
            "value" : 20581813675
          }, {
            "startTime" : 1667754581367,
            "value" : 20936782712
          }, {
            "startTime" : 1667754602304,
            "value" : 20821656874
          }, {
            "startTime" : 1667754623126,
            "value" : 20904054626
          }, {
            "startTime" : 1667754644030,
            "value" : 21218128136
          }, {
            "startTime" : 1667754665248,
            "value" : 20817891558
          }, {
            "startTime" : 1667754686066,
            "value" : 21468061310
          }, {
            "startTime" : 1667754707534,
            "value" : 21239373271
          } ]
        }
      } ]
    } ]
  } ]
}