{
  "clazz" : "org.apache.commons.fileupload.ServletFileUploadTest",
  "methods" : [ {
    "method" : "testWithNullContentType",
    "datacollectorResults" : [ {
      "name" : "de.dagere.kopeme.datacollection.TimeDataCollectorNoGC",
      "chunks" : [ ],
      "results" : [ {
        "value" : 2.8744673176000004E9,
        "deviation" : 0.03469810053381601,
        "min" : 2.814090682E9,
        "max" : 3.151082137E9,
        "warmup" : 0,
        "iterations" : 10,
        "repetitions" : 1000000,
        "commit" : null,
        "vmRunConfiguration" : {
          "showStart" : false,
          "executeBeforeClassInMeasurement" : false,
          "redirectToTemp" : false,
          "redirectToNull" : true,
          "useKieker" : false
        },
        "javaVersion" : "1.8.0_312",
        "cpu" : "model name : Intel(R) Core(TM) i7-4770 CPU @ 3.40GHz",
        "memory" : "MemTotal: 16280696 kB",
        "date" : 1667970441174,
        "fulldata" : {
          "fileName" : null,
          "values" : [ {
            "startTime" : 1667970412260,
            "value" : 3151082137
          }, {
            "startTime" : 1667970415412,
            "value" : 2893565914
          }, {
            "startTime" : 1667970418305,
            "value" : 2829538888
          }, {
            "startTime" : 1667970421135,
            "value" : 2827890795
          }, {
            "startTime" : 1667970423963,
            "value" : 2838286362
          }, {
            "startTime" : 1667970426801,
            "value" : 2866434969
          }, {
            "startTime" : 1667970429668,
            "value" : 2850670478
          }, {
            "startTime" : 1667970432518,
            "value" : 2837529411
          }, {
            "startTime" : 1667970435356,
            "value" : 2814090682
          }, {
            "startTime" : 1667970438170,
            "value" : 2835583540
          } ]
        }
      } ]
    } ]
  } ]
}