{
  "clazz" : "org.apache.commons.fileupload.ParameterParserTest",
  "methods" : [ {
    "method" : "fileUpload199",
    "datacollectorResults" : [ {
      "name" : "de.dagere.kopeme.datacollection.TimeDataCollectorNoGC",
      "chunks" : [ ],
      "results" : [ {
        "value" : 1.6484081021999998E9,
        "deviation" : 0.06578983393085822,
        "min" : 1.575602763E9,
        "max" : 1.927094469E9,
        "warmup" : 0,
        "iterations" : 10,
        "repetitions" : 1000000,
        "commit" : null,
        "vmRunConfiguration" : {
          "showStart" : false,
          "executeBeforeClassInMeasurement" : false,
          "redirectToTemp" : false,
          "redirectToNull" : true,
          "useKieker" : false
        },
        "javaVersion" : "1.8.0_312",
        "cpu" : "model name : Intel(R) Core(TM) i7-4770 CPU @ 3.40GHz",
        "memory" : "MemTotal: 16280696 kB",
        "date" : 1667737661419,
        "fulldata" : {
          "fileName" : null,
          "values" : [ {
            "startTime" : 1667737644770,
            "value" : 1927094469
          }, {
            "startTime" : 1667737646697,
            "value" : 1703568541
          }, {
            "startTime" : 1667737648401,
            "value" : 1688581674
          }, {
            "startTime" : 1667737650089,
            "value" : 1643893490
          }, {
            "startTime" : 1667737651733,
            "value" : 1576509195
          }, {
            "startTime" : 1667737653310,
            "value" : 1575602763
          }, {
            "startTime" : 1667737654885,
            "value" : 1576187143
          }, {
            "startTime" : 1667737656462,
            "value" : 1592111980
          }, {
            "startTime" : 1667737658054,
            "value" : 1597429909
          }, {
            "startTime" : 1667737659651,
            "value" : 1603101858
          } ]
        }
      } ]
    } ]
  } ]
}