{
  "clazz" : "org.apache.commons.fileupload.SizesTest",
  "methods" : [ {
    "method" : "testFileUpload",
    "datacollectorResults" : [ {
      "name" : "de.dagere.kopeme.datacollection.TimeDataCollectorNoGC",
      "chunks" : [ ],
      "results" : [ {
        "value" : 1.3439306963600002E10,
        "deviation" : 0.025069322964064406,
        "min" : 1.3245136231E10,
        "max" : 1.43841766E10,
        "warmup" : 0,
        "iterations" : 10,
        "repetitions" : 320,
        "commit" : null,
        "vmRunConfiguration" : {
          "showStart" : false,
          "executeBeforeClassInMeasurement" : false,
          "redirectToTemp" : false,
          "redirectToNull" : true,
          "useKieker" : false
        },
        "javaVersion" : "1.8.0_312",
        "cpu" : "model name : Intel(R) Core(TM) i7-4770 CPU @ 3.40GHz",
        "memory" : "MemTotal: 16280696 kB",
        "date" : 1667838896183,
        "fulldata" : {
          "fileName" : null,
          "values" : [ {
            "startTime" : 1667838761581,
            "value" : 14384176600
          }, {
            "startTime" : 1667838775965,
            "value" : 13365834779
          }, {
            "startTime" : 1667838789331,
            "value" : 13287414017
          }, {
            "startTime" : 1667838802618,
            "value" : 13266520531
          }, {
            "startTime" : 1667838815885,
            "value" : 13331754379
          }, {
            "startTime" : 1667838829217,
            "value" : 13367603973
          }, {
            "startTime" : 1667838842584,
            "value" : 13442644795
          }, {
            "startTime" : 1667838856027,
            "value" : 13366430147
          }, {
            "startTime" : 1667838869394,
            "value" : 13335554184
          }, {
            "startTime" : 1667838882729,
            "value" : 13245136231
          } ]
        }
      } ]
    } ]
  } ]
}