{
  "clazz" : "org.apache.commons.fileupload.SizesTest",
  "methods" : [ {
    "method" : "testFileUpload",
    "datacollectorResults" : [ {
      "name" : "de.dagere.kopeme.datacollection.TimeDataCollectorNoGC",
      "chunks" : [ ],
      "results" : [ {
        "value" : 1.3171838392400002E10,
        "deviation" : 0.02394706171879369,
        "min" : 1.2983430585E10,
        "max" : 1.4052643049E10,
        "warmup" : 0,
        "iterations" : 10,
        "repetitions" : 320,
        "commit" : null,
        "vmRunConfiguration" : {
          "showStart" : false,
          "executeBeforeClassInMeasurement" : false,
          "redirectToTemp" : false,
          "redirectToNull" : true,
          "useKieker" : false
        },
        "javaVersion" : "1.8.0_312",
        "cpu" : "model name : Intel(R) Core(TM) i7-4770 CPU @ 3.40GHz",
        "memory" : "MemTotal: 16280696 kB",
        "date" : 1668030128336,
        "fulldata" : {
          "fileName" : null,
          "values" : [ {
            "startTime" : 1668029996330,
            "value" : 14052643049
          }, {
            "startTime" : 1668030010382,
            "value" : 13048341038
          }, {
            "startTime" : 1668030023431,
            "value" : 13057447299
          }, {
            "startTime" : 1668030036488,
            "value" : 13056381920
          }, {
            "startTime" : 1668030049545,
            "value" : 12983430585
          }, {
            "startTime" : 1668030062528,
            "value" : 13177657303
          }, {
            "startTime" : 1668030075706,
            "value" : 13124244212
          }, {
            "startTime" : 1668030088830,
            "value" : 12988539476
          }, {
            "startTime" : 1668030101819,
            "value" : 13108838442
          }, {
            "startTime" : 1668030114928,
            "value" : 13120860600
          } ]
        }
      } ]
    } ]
  } ]
}