{
  "clazz" : "org.apache.commons.fileupload.SizesTest",
  "methods" : [ {
    "method" : "testFileUpload",
    "datacollectorResults" : [ {
      "name" : "de.dagere.kopeme.datacollection.TimeDataCollectorNoGC",
      "chunks" : [ ],
      "results" : [ {
        "value" : 1.34038811299E10,
        "deviation" : 0.02835821287510793,
        "min" : 1.3190427129E10,
        "max" : 1.4465722377E10,
        "warmup" : 0,
        "iterations" : 10,
        "repetitions" : 320,
        "commit" : null,
        "vmRunConfiguration" : {
          "showStart" : false,
          "executeBeforeClassInMeasurement" : false,
          "redirectToTemp" : false,
          "redirectToNull" : true,
          "useKieker" : false
        },
        "javaVersion" : "1.8.0_312",
        "cpu" : "model name : Intel(R) Core(TM) i7-4770 CPU @ 3.40GHz",
        "memory" : "MemTotal: 16280696 kB",
        "date" : 1667750114148,
        "fulldata" : {
          "fileName" : null,
          "values" : [ {
            "startTime" : 1667749979843,
            "value" : 14465722377
          }, {
            "startTime" : 1667749994309,
            "value" : 13407629348
          }, {
            "startTime" : 1667750007717,
            "value" : 13317856516
          }, {
            "startTime" : 1667750021035,
            "value" : 13273546331
          }, {
            "startTime" : 1667750034309,
            "value" : 13291630344
          }, {
            "startTime" : 1667750047600,
            "value" : 13190427129
          }, {
            "startTime" : 1667750060791,
            "value" : 13377576521
          }, {
            "startTime" : 1667750074168,
            "value" : 13209515164
          }, {
            "startTime" : 1667750087378,
            "value" : 13307004780
          }, {
            "startTime" : 1667750100685,
            "value" : 13197902789
          } ]
        }
      } ]
    } ]
  } ]
}