{
  "clazz" : "org.apache.commons.fileupload.ServletFileUploadTest",
  "methods" : [ {
    "method" : "testWithNullContentType",
    "datacollectorResults" : [ {
      "name" : "de.dagere.kopeme.datacollection.TimeDataCollectorNoGC",
      "chunks" : [ ],
      "results" : [ {
        "value" : 2.7259839576E9,
        "deviation" : 0.045245321666211605,
        "min" : 2.670224532E9,
        "max" : 3.069533217E9,
        "warmup" : 0,
        "iterations" : 10,
        "repetitions" : 1000000,
        "commit" : null,
        "vmRunConfiguration" : {
          "showStart" : false,
          "executeBeforeClassInMeasurement" : false,
          "redirectToTemp" : false,
          "redirectToNull" : true,
          "useKieker" : false
        },
        "javaVersion" : "1.8.0_312",
        "cpu" : "model name : Intel(R) Core(TM) i7-4770 CPU @ 3.40GHz",
        "memory" : "MemTotal: 16280696 kB",
        "date" : 1667798655173,
        "fulldata" : {
          "fileName" : null,
          "values" : [ {
            "startTime" : 1667798627735,
            "value" : 3069533217
          }, {
            "startTime" : 1667798630805,
            "value" : 2731388938
          }, {
            "startTime" : 1667798633536,
            "value" : 2738270053
          }, {
            "startTime" : 1667798636274,
            "value" : 2673174554
          }, {
            "startTime" : 1667798638948,
            "value" : 2676585070
          }, {
            "startTime" : 1667798641624,
            "value" : 2675341573
          }, {
            "startTime" : 1667798644300,
            "value" : 2672164996
          }, {
            "startTime" : 1667798646972,
            "value" : 2679968677
          }, {
            "startTime" : 1667798649652,
            "value" : 2670224532
          }, {
            "startTime" : 1667798652322,
            "value" : 2673187966
          } ]
        }
      } ]
    } ]
  } ]
}