{
  "clazz" : "org.apache.commons.fileupload.StreamingTest",
  "methods" : [ {
    "method" : "testFileUploadException",
    "datacollectorResults" : [ {
      "name" : "de.dagere.kopeme.datacollection.TimeDataCollectorNoGC",
      "chunks" : [ ],
      "results" : [ {
        "value" : 6.0029551314E10,
        "deviation" : 0.46974924182021377,
        "min" : 9.614321383E9,
        "max" : 7.4266626192E10,
        "warmup" : 0,
        "iterations" : 5,
        "repetitions" : 1600,
        "commit" : null,
        "vmRunConfiguration" : {
          "showStart" : false,
          "executeBeforeClassInMeasurement" : false,
          "redirectToTemp" : false,
          "redirectToNull" : true,
          "useKieker" : false
        },
        "javaVersion" : "1.8.0_312",
        "cpu" : "model name : Intel(R) Core(TM) i7-4770 CPU @ 3.40GHz",
        "memory" : "MemTotal: 16280696 kB",
        "date" : 1667773511272,
        "error" : true,
        "fulldata" : {
          "fileName" : null,
          "values" : [ {
            "startTime" : 1667773210967,
            "value" : 74266626192
          }, {
            "startTime" : 1667773285234,
            "value" : 71972863803
          }, {
            "startTime" : 1667773357207,
            "value" : 72122117666
          }, {
            "startTime" : 1667773429329,
            "value" : 72171827526
          }, {
            "startTime" : 1667773501501,
            "value" : 9614321383
          } ]
        }
      } ]
    } ]
  } ]
}