{
  "clazz" : "org.apache.commons.fileupload.SizesTest",
  "methods" : [ {
    "method" : "testFileUpload",
    "datacollectorResults" : [ {
      "name" : "de.dagere.kopeme.datacollection.TimeDataCollectorNoGC",
      "chunks" : [ ],
      "results" : [ {
        "value" : 1.34431114619E10,
        "deviation" : 0.029527192713327047,
        "min" : 1.3240509608E10,
        "max" : 1.4558543325E10,
        "warmup" : 0,
        "iterations" : 10,
        "repetitions" : 320,
        "commit" : null,
        "vmRunConfiguration" : {
          "showStart" : false,
          "executeBeforeClassInMeasurement" : false,
          "redirectToTemp" : false,
          "redirectToNull" : true,
          "useKieker" : false
        },
        "javaVersion" : "1.8.0_312",
        "cpu" : "model name : Intel(R) Core(TM) i7-4770 CPU @ 3.40GHz",
        "memory" : "MemTotal: 16280696 kB",
        "date" : 1667716194590,
        "fulldata" : {
          "fileName" : null,
          "values" : [ {
            "startTime" : 1667716059927,
            "value" : 14558543325
          }, {
            "startTime" : 1667716074485,
            "value" : 13440580572
          }, {
            "startTime" : 1667716087926,
            "value" : 13251905995
          }, {
            "startTime" : 1667716101178,
            "value" : 13276734135
          }, {
            "startTime" : 1667716114455,
            "value" : 13240509608
          }, {
            "startTime" : 1667716127695,
            "value" : 13296053489
          }, {
            "startTime" : 1667716140991,
            "value" : 13286381967
          }, {
            "startTime" : 1667716154278,
            "value" : 13388829423
          }, {
            "startTime" : 1667716167667,
            "value" : 13361114010
          }, {
            "startTime" : 1667716181028,
            "value" : 13330462095
          } ]
        }
      } ]
    } ]
  } ]
}