{
  "clazz" : "org.apache.commons.fileupload.DiskFileItemSerializeTest",
  "methods" : [ {
    "method" : "testBelowThreshold",
    "datacollectorResults" : [ {
      "name" : "de.dagere.kopeme.datacollection.TimeDataCollectorNoGC",
      "chunks" : [ ],
      "results" : [ {
        "value" : 3.705204488E9,
        "deviation" : 0.12565517635339757,
        "min" : 3.446339577E9,
        "max" : 5.018119399E9,
        "warmup" : 0,
        "iterations" : 10,
        "repetitions" : 200000,
        "commit" : null,
        "vmRunConfiguration" : {
          "showStart" : false,
          "executeBeforeClassInMeasurement" : false,
          "redirectToTemp" : false,
          "redirectToNull" : true,
          "useKieker" : false
        },
        "javaVersion" : "1.8.0_312",
        "cpu" : "model name : Intel(R) Core(TM) i7-4770 CPU @ 3.40GHz",
        "memory" : "MemTotal: 16280696 kB",
        "date" : 1667920993006,
        "fulldata" : {
          "fileName" : null,
          "values" : [ {
            "startTime" : 1667920955673,
            "value" : 5018119399
          }, {
            "startTime" : 1667920960691,
            "value" : 3641949472
          }, {
            "startTime" : 1667920964333,
            "value" : 3552027901
          }, {
            "startTime" : 1667920967885,
            "value" : 3623608236
          }, {
            "startTime" : 1667920971509,
            "value" : 3532233652
          }, {
            "startTime" : 1667920975041,
            "value" : 3471447075
          }, {
            "startTime" : 1667920978512,
            "value" : 3579027701
          }, {
            "startTime" : 1667920982091,
            "value" : 3611187894
          }, {
            "startTime" : 1667920985703,
            "value" : 3446339577
          }, {
            "startTime" : 1667920989149,
            "value" : 3576103973
          } ]
        }
      } ]
    } ]
  } ]
}