{
  "clazz" : "org.apache.commons.fileupload.MultipartStreamTest",
  "methods" : [ {
    "method" : "testSmallBuffer",
    "datacollectorResults" : [ {
      "name" : "de.dagere.kopeme.datacollection.TimeDataCollectorNoGC",
      "chunks" : [ ],
      "results" : [ {
        "value" : 1.7937594913E9,
        "deviation" : 0.015568007628494234,
        "min" : 1.752810248E9,
        "max" : 1.841965758E9,
        "warmup" : 0,
        "iterations" : 10,
        "repetitions" : 1000000,
        "commit" : null,
        "vmRunConfiguration" : {
          "showStart" : false,
          "executeBeforeClassInMeasurement" : false,
          "redirectToTemp" : false,
          "redirectToNull" : true,
          "useKieker" : false
        },
        "javaVersion" : "1.8.0_312",
        "cpu" : "model name : Intel(R) Core(TM) i7-4770 CPU @ 3.40GHz",
        "memory" : "MemTotal: 16280696 kB",
        "date" : 1667804935280,
        "fulldata" : {
          "fileName" : null,
          "values" : [ {
            "startTime" : 1667804917184,
            "value" : 1828679462
          }, {
            "startTime" : 1667804919013,
            "value" : 1811568711
          }, {
            "startTime" : 1667804920824,
            "value" : 1803298820
          }, {
            "startTime" : 1667804922628,
            "value" : 1786498427
          }, {
            "startTime" : 1667804924414,
            "value" : 1788408800
          }, {
            "startTime" : 1667804926203,
            "value" : 1786253387
          }, {
            "startTime" : 1667804927989,
            "value" : 1773047630
          }, {
            "startTime" : 1667804929762,
            "value" : 1752810248
          }, {
            "startTime" : 1667804931515,
            "value" : 1765063670
          }, {
            "startTime" : 1667804933280,
            "value" : 1841965758
          } ]
        }
      } ]
    } ]
  } ]
}