{
  "clazz" : "org.apache.commons.fileupload.StreamingTest",
  "methods" : [ {
    "method" : "testFileUploadException",
    "datacollectorResults" : [ {
      "name" : "de.dagere.kopeme.datacollection.TimeDataCollectorNoGC",
      "chunks" : [ ],
      "results" : [ {
        "value" : 1.4221895243299997E10,
        "deviation" : 0.0544319610731813,
        "min" : 1.3866172274E10,
        "max" : 1.640945727E10,
        "warmup" : 0,
        "iterations" : 10,
        "repetitions" : 320,
        "commit" : null,
        "vmRunConfiguration" : {
          "showStart" : false,
          "executeBeforeClassInMeasurement" : false,
          "redirectToTemp" : false,
          "redirectToNull" : true,
          "useKieker" : false
        },
        "javaVersion" : "1.8.0_312",
        "cpu" : "model name : Intel(R) Core(TM) i7-4770 CPU @ 3.40GHz",
        "memory" : "MemTotal: 16280696 kB",
        "date" : 1667833576988,
        "fulldata" : {
          "fileName" : null,
          "values" : [ {
            "startTime" : 1667833434572,
            "value" : 16409457270
          }, {
            "startTime" : 1667833450981,
            "value" : 13866172274
          }, {
            "startTime" : 1667833464848,
            "value" : 13868521717
          }, {
            "startTime" : 1667833478716,
            "value" : 13994212727
          }, {
            "startTime" : 1667833492710,
            "value" : 14032136634
          }, {
            "startTime" : 1667833506743,
            "value" : 13910368922
          }, {
            "startTime" : 1667833520653,
            "value" : 13893537071
          }, {
            "startTime" : 1667833534547,
            "value" : 14030098440
          }, {
            "startTime" : 1667833548577,
            "value" : 14127158990
          }, {
            "startTime" : 1667833562704,
            "value" : 14087288388
          } ]
        }
      } ]
    } ]
  } ]
}