{
  "clazz" : "org.apache.commons.fileupload.SizesTest",
  "methods" : [ {
    "method" : "testFileSizeLimit",
    "datacollectorResults" : [ {
      "name" : "de.dagere.kopeme.datacollection.TimeDataCollectorNoGC",
      "chunks" : [ ],
      "results" : [ {
        "value" : 9.296695572000002E9,
        "deviation" : 0.045734624402732134,
        "min" : 8.988569585E9,
        "max" : 1.044805927E10,
        "warmup" : 0,
        "iterations" : 10,
        "repetitions" : 200000,
        "commit" : null,
        "vmRunConfiguration" : {
          "showStart" : false,
          "executeBeforeClassInMeasurement" : false,
          "redirectToTemp" : false,
          "redirectToNull" : true,
          "useKieker" : false
        },
        "javaVersion" : "1.8.0_312",
        "cpu" : "model name : Intel(R) Core(TM) i7-4770 CPU @ 3.40GHz",
        "memory" : "MemTotal: 16280696 kB",
        "date" : 1667849914583,
        "fulldata" : {
          "fileName" : null,
          "values" : [ {
            "startTime" : 1667849821353,
            "value" : 10448059270
          }, {
            "startTime" : 1667849831801,
            "value" : 9138083701
          }, {
            "startTime" : 1667849840939,
            "value" : 9030396946
          }, {
            "startTime" : 1667849849970,
            "value" : 8988569585
          }, {
            "startTime" : 1667849858958,
            "value" : 9198132053
          }, {
            "startTime" : 1667849868156,
            "value" : 9057203923
          }, {
            "startTime" : 1667849877214,
            "value" : 9197613505
          }, {
            "startTime" : 1667849886411,
            "value" : 9223173859
          }, {
            "startTime" : 1667849895635,
            "value" : 9233774169
          }, {
            "startTime" : 1667849904868,
            "value" : 9451948709
          } ]
        }
      } ]
    } ]
  } ]
}