{
  "clazz" : "org.apache.commons.fileupload.util.mime.Base64DecoderTestCase",
  "methods" : [ {
    "method" : "rfc4648Section10Decode",
    "datacollectorResults" : [ {
      "name" : "de.dagere.kopeme.datacollection.TimeDataCollectorNoGC",
      "chunks" : [ ],
      "results" : [ {
        "value" : 9.058141009E8,
        "deviation" : 0.08230653393241057,
        "min" : 8.47998264E8,
        "max" : 1.058059155E9,
        "warmup" : 0,
        "iterations" : 10,
        "repetitions" : 1000000,
        "commit" : null,
        "vmRunConfiguration" : {
          "showStart" : false,
          "executeBeforeClassInMeasurement" : false,
          "redirectToTemp" : false,
          "redirectToNull" : true,
          "useKieker" : false
        },
        "javaVersion" : "1.8.0_312",
        "cpu" : "model name : Intel(R) Core(TM) i7-4770 CPU @ 3.40GHz",
        "memory" : "MemTotal: 16280696 kB",
        "date" : 1667744864050,
        "fulldata" : {
          "fileName" : null,
          "values" : [ {
            "startTime" : 1667744854816,
            "value" : 1058059155
          }, {
            "startTime" : 1667744855874,
            "value" : 983509672
          }, {
            "startTime" : 1667744856858,
            "value" : 982252288
          }, {
            "startTime" : 1667744857840,
            "value" : 859366294
          }, {
            "startTime" : 1667744858699,
            "value" : 848673131
          }, {
            "startTime" : 1667744859548,
            "value" : 865480303
          }, {
            "startTime" : 1667744860414,
            "value" : 859928795
          }, {
            "startTime" : 1667744861273,
            "value" : 857152097
          }, {
            "startTime" : 1667744862131,
            "value" : 847998264
          }, {
            "startTime" : 1667744862979,
            "value" : 895721010
          } ]
        }
      } ]
    } ]
  } ]
}