{
  "clazz" : "org.apache.commons.fileupload.util.mime.QuotedPrintableDecoderTestCase",
  "methods" : [ {
    "method" : "basicEncodeDecode",
    "datacollectorResults" : [ {
      "name" : "de.dagere.kopeme.datacollection.TimeDataCollectorNoGC",
      "chunks" : [ ],
      "results" : [ {
        "value" : 3.828542521E8,
        "deviation" : 0.3358401141824864,
        "min" : 1.98366186E8,
        "max" : 5.06857202E8,
        "warmup" : 0,
        "iterations" : 10,
        "repetitions" : 1000000,
        "commit" : null,
        "vmRunConfiguration" : {
          "showStart" : false,
          "executeBeforeClassInMeasurement" : false,
          "redirectToTemp" : false,
          "redirectToNull" : true,
          "useKieker" : false
        },
        "javaVersion" : "1.8.0_312",
        "cpu" : "model name : Intel(R) Core(TM) i7-4770 CPU @ 3.40GHz",
        "memory" : "MemTotal: 16280696 kB",
        "date" : 1667739655206,
        "fulldata" : {
          "fileName" : null,
          "values" : [ {
            "startTime" : 1667739651204,
            "value" : 506857202
          }, {
            "startTime" : 1667739651711,
            "value" : 465367463
          }, {
            "startTime" : 1667739652177,
            "value" : 462360855
          }, {
            "startTime" : 1667739652639,
            "value" : 463796972
          }, {
            "startTime" : 1667739653103,
            "value" : 465223424
          }, {
            "startTime" : 1667739653568,
            "value" : 464398145
          }, {
            "startTime" : 1667739654033,
            "value" : 399699226
          }, {
            "startTime" : 1667739654432,
            "value" : 198366186
          }, {
            "startTime" : 1667739654631,
            "value" : 203288595
          }, {
            "startTime" : 1667739654834,
            "value" : 199184453
          } ]
        }
      } ]
    } ]
  } ]
}