{
  "clazz" : "org.apache.commons.fileupload.util.mime.QuotedPrintableDecoderTestCase",
  "methods" : [ {
    "method" : "basicEncodeDecode",
    "datacollectorResults" : [ {
      "name" : "de.dagere.kopeme.datacollection.TimeDataCollectorNoGC",
      "chunks" : [ ],
      "results" : [ {
        "value" : 2.6166478700000003E8,
        "deviation" : 0.1279346959467597,
        "min" : 2.45409047E8,
        "max" : 3.54656703E8,
        "warmup" : 0,
        "iterations" : 10,
        "repetitions" : 1000000,
        "commit" : null,
        "vmRunConfiguration" : {
          "showStart" : false,
          "executeBeforeClassInMeasurement" : false,
          "redirectToTemp" : false,
          "redirectToNull" : true,
          "useKieker" : false
        },
        "javaVersion" : "1.8.0_312",
        "cpu" : "model name : Intel(R) Core(TM) i7-4770 CPU @ 3.40GHz",
        "memory" : "MemTotal: 16280696 kB",
        "date" : 1667740004789,
        "fulldata" : {
          "fileName" : null,
          "values" : [ {
            "startTime" : 1667740002008,
            "value" : 354656703
          }, {
            "startTime" : 1667740002363,
            "value" : 267521860
          }, {
            "startTime" : 1667740002630,
            "value" : 254551887
          }, {
            "startTime" : 1667740002885,
            "value" : 245865763
          }, {
            "startTime" : 1667740003131,
            "value" : 247116541
          }, {
            "startTime" : 1667740003378,
            "value" : 245409047
          }, {
            "startTime" : 1667740003623,
            "value" : 247066811
          }, {
            "startTime" : 1667740003870,
            "value" : 246884148
          }, {
            "startTime" : 1667740004117,
            "value" : 247778744
          }, {
            "startTime" : 1667740004365,
            "value" : 259796366
          } ]
        }
      } ]
    } ]
  } ]
}