{
  "clazz" : "org.apache.commons.fileupload.ParameterParserTest",
  "methods" : [ {
    "method" : "fileUpload199",
    "datacollectorResults" : [ {
      "name" : "de.dagere.kopeme.datacollection.TimeDataCollectorNoGC",
      "chunks" : [ ],
      "results" : [ {
        "value" : 1.7084403761E9,
        "deviation" : 0.05890437900155542,
        "min" : 1.63583561E9,
        "max" : 1.968355074E9,
        "warmup" : 0,
        "iterations" : 10,
        "repetitions" : 1000000,
        "commit" : null,
        "vmRunConfiguration" : {
          "showStart" : false,
          "executeBeforeClassInMeasurement" : false,
          "redirectToTemp" : false,
          "redirectToNull" : true,
          "useKieker" : false
        },
        "javaVersion" : "1.8.0_312",
        "cpu" : "model name : Intel(R) Core(TM) i7-4770 CPU @ 3.40GHz",
        "memory" : "MemTotal: 16280696 kB",
        "date" : 1667725011376,
        "fulldata" : {
          "fileName" : null,
          "values" : [ {
            "startTime" : 1667724994058,
            "value" : 1968355074
          }, {
            "startTime" : 1667724996026,
            "value" : 1736129019
          }, {
            "startTime" : 1667724997762,
            "value" : 1665946811
          }, {
            "startTime" : 1667724999428,
            "value" : 1650473893
          }, {
            "startTime" : 1667725001079,
            "value" : 1635835610
          }, {
            "startTime" : 1667725002715,
            "value" : 1654581698
          }, {
            "startTime" : 1667725004369,
            "value" : 1647738739
          }, {
            "startTime" : 1667725006017,
            "value" : 1687522877
          }, {
            "startTime" : 1667725007705,
            "value" : 1668194413
          }, {
            "startTime" : 1667725009373,
            "value" : 1769625627
          } ]
        }
      } ]
    } ]
  } ]
}