{
  "clazz" : "org.apache.commons.fileupload.SizesTest",
  "methods" : [ {
    "method" : "testFileUpload",
    "datacollectorResults" : [ {
      "name" : "de.dagere.kopeme.datacollection.TimeDataCollectorNoGC",
      "chunks" : [ ],
      "results" : [ {
        "value" : 1.30833498764E10,
        "deviation" : 0.02455580298854824,
        "min" : 1.2875558011E10,
        "max" : 1.3987288231E10,
        "warmup" : 0,
        "iterations" : 10,
        "repetitions" : 320,
        "commit" : null,
        "vmRunConfiguration" : {
          "showStart" : false,
          "executeBeforeClassInMeasurement" : false,
          "redirectToTemp" : false,
          "redirectToNull" : true,
          "useKieker" : false
        },
        "javaVersion" : "1.8.0_312",
        "cpu" : "model name : Intel(R) Core(TM) i7-4770 CPU @ 3.40GHz",
        "memory" : "MemTotal: 16280696 kB",
        "date" : 1667944510135,
        "fulldata" : {
          "fileName" : null,
          "values" : [ {
            "startTime" : 1667944379042,
            "value" : 13987288231
          }, {
            "startTime" : 1667944393029,
            "value" : 13024590328
          }, {
            "startTime" : 1667944406054,
            "value" : 13002667965
          }, {
            "startTime" : 1667944419057,
            "value" : 12957497070
          }, {
            "startTime" : 1667944432014,
            "value" : 12982838157
          }, {
            "startTime" : 1667944444997,
            "value" : 13063393345
          }, {
            "startTime" : 1667944458061,
            "value" : 12875558011
          }, {
            "startTime" : 1667944470936,
            "value" : 12977876598
          }, {
            "startTime" : 1667944483914,
            "value" : 12969954954
          }, {
            "startTime" : 1667944496884,
            "value" : 12991834105
          } ]
        }
      } ]
    } ]
  } ]
}