{
  "clazz" : "org.apache.commons.fileupload.SizesTest",
  "methods" : [ {
    "method" : "testFileUpload",
    "datacollectorResults" : [ {
      "name" : "de.dagere.kopeme.datacollection.TimeDataCollectorNoGC",
      "chunks" : [ ],
      "results" : [ {
        "value" : 1.31984678947E10,
        "deviation" : 0.02254349537423655,
        "min" : 1.3025503205E10,
        "max" : 1.4027012385E10,
        "warmup" : 0,
        "iterations" : 10,
        "repetitions" : 320,
        "commit" : null,
        "vmRunConfiguration" : {
          "showStart" : false,
          "executeBeforeClassInMeasurement" : false,
          "redirectToTemp" : false,
          "redirectToNull" : true,
          "useKieker" : false
        },
        "javaVersion" : "1.8.0_312",
        "cpu" : "model name : Intel(R) Core(TM) i7-4770 CPU @ 3.40GHz",
        "memory" : "MemTotal: 16280696 kB",
        "date" : 1667945835752,
        "fulldata" : {
          "fileName" : null,
          "values" : [ {
            "startTime" : 1667945703519,
            "value" : 14027012385
          }, {
            "startTime" : 1667945717546,
            "value" : 13025503205
          }, {
            "startTime" : 1667945730571,
            "value" : 13111237086
          }, {
            "startTime" : 1667945743682,
            "value" : 13068728219
          }, {
            "startTime" : 1667945756751,
            "value" : 13176282730
          }, {
            "startTime" : 1667945769928,
            "value" : 13036146304
          }, {
            "startTime" : 1667945782964,
            "value" : 13201500402
          }, {
            "startTime" : 1667945796165,
            "value" : 13046347282
          }, {
            "startTime" : 1667945809212,
            "value" : 13160445018
          }, {
            "startTime" : 1667945822372,
            "value" : 13131476316
          } ]
        }
      } ]
    } ]
  } ]
}