{
  "clazz" : "org.apache.commons.fileupload.util.mime.Base64DecoderTestCase",
  "methods" : [ {
    "method" : "rfc4648Section10Decode",
    "datacollectorResults" : [ {
      "name" : "de.dagere.kopeme.datacollection.TimeDataCollectorNoGC",
      "chunks" : [ ],
      "results" : [ {
        "value" : 8.795983415E8,
        "deviation" : 0.14896285243471544,
        "min" : 8.14186026E8,
        "max" : 1.250678265E9,
        "warmup" : 0,
        "iterations" : 10,
        "repetitions" : 1000000,
        "commit" : null,
        "vmRunConfiguration" : {
          "showStart" : false,
          "executeBeforeClassInMeasurement" : false,
          "redirectToTemp" : false,
          "redirectToNull" : true,
          "useKieker" : false
        },
        "javaVersion" : "1.8.0_312",
        "cpu" : "model name : Intel(R) Core(TM) i7-4770 CPU @ 3.40GHz",
        "memory" : "MemTotal: 16280696 kB",
        "date" : 1667746425461,
        "fulldata" : {
          "fileName" : null,
          "values" : [ {
            "startTime" : 1667746416449,
            "value" : 1250678265
          }, {
            "startTime" : 1667746417700,
            "value" : 824563819
          }, {
            "startTime" : 1667746418525,
            "value" : 831455156
          }, {
            "startTime" : 1667746419356,
            "value" : 841651717
          }, {
            "startTime" : 1667746420198,
            "value" : 852502392
          }, {
            "startTime" : 1667746421050,
            "value" : 859032268
          }, {
            "startTime" : 1667746421909,
            "value" : 814186026
          }, {
            "startTime" : 1667746422724,
            "value" : 843000530
          }, {
            "startTime" : 1667746423567,
            "value" : 843260484
          }, {
            "startTime" : 1667746424410,
            "value" : 835652758
          } ]
        }
      } ]
    } ]
  } ]
}