{
  "clazz" : "org.apache.commons.fileupload.SizesTest",
  "methods" : [ {
    "method" : "testFileUpload",
    "datacollectorResults" : [ {
      "name" : "de.dagere.kopeme.datacollection.TimeDataCollectorNoGC",
      "chunks" : [ ],
      "results" : [ {
        "value" : 1.35359816939E10,
        "deviation" : 0.022750525624518417,
        "min" : 1.3354852475E10,
        "max" : 1.4400166814E10,
        "warmup" : 0,
        "iterations" : 10,
        "repetitions" : 320,
        "commit" : null,
        "vmRunConfiguration" : {
          "showStart" : false,
          "executeBeforeClassInMeasurement" : false,
          "redirectToTemp" : false,
          "redirectToNull" : true,
          "useKieker" : false
        },
        "javaVersion" : "1.8.0_312",
        "cpu" : "model name : Intel(R) Core(TM) i7-4770 CPU @ 3.40GHz",
        "memory" : "MemTotal: 16280696 kB",
        "date" : 1667861241862,
        "fulldata" : {
          "fileName" : null,
          "values" : [ {
            "startTime" : 1667861106223,
            "value" : 14400166814
          }, {
            "startTime" : 1667861120623,
            "value" : 13474204215
          }, {
            "startTime" : 1667861134098,
            "value" : 13482211083
          }, {
            "startTime" : 1667861147580,
            "value" : 13358192708
          }, {
            "startTime" : 1667861160938,
            "value" : 13466953595
          }, {
            "startTime" : 1667861174405,
            "value" : 13411517205
          }, {
            "startTime" : 1667861187817,
            "value" : 13430283697
          }, {
            "startTime" : 1667861201247,
            "value" : 13494976903
          }, {
            "startTime" : 1667861214742,
            "value" : 13354852475
          }, {
            "startTime" : 1667861228097,
            "value" : 13486458244
          } ]
        }
      } ]
    } ]
  } ]
}