{
  "clazz" : "org.apache.commons.fileupload.ServletFileUploadTest",
  "methods" : [ {
    "method" : "testWithNullContentType",
    "datacollectorResults" : [ {
      "name" : "de.dagere.kopeme.datacollection.TimeDataCollectorNoGC",
      "chunks" : [ ],
      "results" : [ {
        "value" : 2.9003627962000003E9,
        "deviation" : 0.030282849969431577,
        "min" : 2.850825802E9,
        "max" : 3.142209849E9,
        "warmup" : 0,
        "iterations" : 10,
        "repetitions" : 1000000,
        "commit" : null,
        "vmRunConfiguration" : {
          "showStart" : false,
          "executeBeforeClassInMeasurement" : false,
          "redirectToTemp" : false,
          "redirectToNull" : true,
          "useKieker" : false
        },
        "javaVersion" : "1.8.0_312",
        "cpu" : "model name : Intel(R) Core(TM) i7-4770 CPU @ 3.40GHz",
        "memory" : "MemTotal: 16280696 kB",
        "date" : 1667970857922,
        "fulldata" : {
          "fileName" : null,
          "values" : [ {
            "startTime" : 1667970828715,
            "value" : 3142209849
          }, {
            "startTime" : 1667970831858,
            "value" : 2912940157
          }, {
            "startTime" : 1667970834771,
            "value" : 2882391354
          }, {
            "startTime" : 1667970837653,
            "value" : 2861113333
          }, {
            "startTime" : 1667970840514,
            "value" : 2854718436
          }, {
            "startTime" : 1667970843369,
            "value" : 2881190580
          }, {
            "startTime" : 1667970846250,
            "value" : 2860732917
          }, {
            "startTime" : 1667970849111,
            "value" : 2851294898
          }, {
            "startTime" : 1667970851962,
            "value" : 2850825802
          }, {
            "startTime" : 1667970854813,
            "value" : 2906210636
          } ]
        }
      } ]
    } ]
  } ]
}