{
  "clazz" : "org.apache.commons.fileupload.ServletFileUploadTest",
  "methods" : [ {
    "method" : "testWithNullContentType",
    "datacollectorResults" : [ {
      "name" : "de.dagere.kopeme.datacollection.TimeDataCollectorNoGC",
      "chunks" : [ ],
      "results" : [ {
        "value" : 2.8487489588E9,
        "deviation" : 0.0404136431957968,
        "min" : 2.791140168E9,
        "max" : 3.167416372E9,
        "warmup" : 0,
        "iterations" : 10,
        "repetitions" : 1000000,
        "commit" : null,
        "vmRunConfiguration" : {
          "showStart" : false,
          "executeBeforeClassInMeasurement" : false,
          "redirectToTemp" : false,
          "redirectToNull" : true,
          "useKieker" : false
        },
        "javaVersion" : "1.8.0_312",
        "cpu" : "model name : Intel(R) Core(TM) i7-4770 CPU @ 3.40GHz",
        "memory" : "MemTotal: 16280696 kB",
        "date" : 1667971146156,
        "fulldata" : {
          "fileName" : null,
          "values" : [ {
            "startTime" : 1667971117491,
            "value" : 3167416372
          }, {
            "startTime" : 1667971120658,
            "value" : 2874968036
          }, {
            "startTime" : 1667971123533,
            "value" : 2814512915
          }, {
            "startTime" : 1667971126348,
            "value" : 2809361059
          }, {
            "startTime" : 1667971129157,
            "value" : 2791809149
          }, {
            "startTime" : 1667971131949,
            "value" : 2791710456
          }, {
            "startTime" : 1667971134741,
            "value" : 2805259591
          }, {
            "startTime" : 1667971137546,
            "value" : 2843534263
          }, {
            "startTime" : 1667971140390,
            "value" : 2791140168
          }, {
            "startTime" : 1667971143181,
            "value" : 2797777579
          } ]
        }
      } ]
    } ]
  } ]
}