{
  "clazz" : "org.apache.commons.fileupload.StreamingTest",
  "methods" : [ {
    "method" : "testFileUploadException",
    "datacollectorResults" : [ {
      "name" : "de.dagere.kopeme.datacollection.TimeDataCollectorNoGC",
      "chunks" : [ ],
      "results" : [ {
        "value" : 6.00332597526E10,
        "deviation" : 0.2551087737462079,
        "min" : 3.2698256133E10,
        "max" : 6.8552611787E10,
        "warmup" : 0,
        "iterations" : 5,
        "repetitions" : 1600,
        "commit" : null,
        "vmRunConfiguration" : {
          "showStart" : false,
          "executeBeforeClassInMeasurement" : false,
          "redirectToTemp" : false,
          "redirectToNull" : true,
          "useKieker" : false
        },
        "javaVersion" : "1.8.0_312",
        "cpu" : "model name : Intel(R) Core(TM) i7-4770 CPU @ 3.40GHz",
        "memory" : "MemTotal: 16280696 kB",
        "date" : 1667994989871,
        "error" : true,
        "fulldata" : {
          "fileName" : null,
          "values" : [ {
            "startTime" : 1667994689551,
            "value" : 68552611787
          }, {
            "startTime" : 1667994758104,
            "value" : 66318855041
          }, {
            "startTime" : 1667994824423,
            "value" : 66749196130
          }, {
            "startTime" : 1667994891172,
            "value" : 65847379672
          }, {
            "startTime" : 1667994957020,
            "value" : 32698256133
          } ]
        }
      } ]
    } ]
  } ]
}