{
  "clazz" : "org.apache.commons.fileupload.SizesTest",
  "methods" : [ {
    "method" : "testMaxSizeLimit",
    "datacollectorResults" : [ {
      "name" : "de.dagere.kopeme.datacollection.TimeDataCollectorNoGC",
      "chunks" : [ ],
      "results" : [ {
        "value" : 3.8017462032999997E9,
        "deviation" : 0.0366019008490116,
        "min" : 3.729963174E9,
        "max" : 4.187189935E9,
        "warmup" : 0,
        "iterations" : 10,
        "repetitions" : 1000000,
        "commit" : null,
        "vmRunConfiguration" : {
          "showStart" : false,
          "executeBeforeClassInMeasurement" : false,
          "redirectToTemp" : false,
          "redirectToNull" : true,
          "useKieker" : false
        },
        "javaVersion" : "1.8.0_312",
        "cpu" : "model name : Intel(R) Core(TM) i7-4770 CPU @ 3.40GHz",
        "memory" : "MemTotal: 16280696 kB",
        "date" : 1667681866394,
        "fulldata" : {
          "fileName" : null,
          "values" : [ {
            "startTime" : 1667681828197,
            "value" : 4187189935
          }, {
            "startTime" : 1667681832384,
            "value" : 3842296636
          }, {
            "startTime" : 1667681836226,
            "value" : 3763616958
          }, {
            "startTime" : 1667681839990,
            "value" : 3738122621
          }, {
            "startTime" : 1667681843728,
            "value" : 3747424123
          }, {
            "startTime" : 1667681847476,
            "value" : 3770827909
          }, {
            "startTime" : 1667681851247,
            "value" : 3736183012
          }, {
            "startTime" : 1667681854983,
            "value" : 3754748743
          }, {
            "startTime" : 1667681858738,
            "value" : 3729963174
          }, {
            "startTime" : 1667681862468,
            "value" : 3747088922
          } ]
        }
      } ]
    } ]
  } ]
}