{
  "clazz" : "org.apache.commons.fileupload.SizesTest",
  "methods" : [ {
    "method" : "testFileUpload",
    "datacollectorResults" : [ {
      "name" : "de.dagere.kopeme.datacollection.TimeDataCollectorNoGC",
      "chunks" : [ ],
      "results" : [ {
        "value" : 1.33555458893E10,
        "deviation" : 0.02317499076023698,
        "min" : 1.3196610911E10,
        "max" : 1.4220120415E10,
        "warmup" : 0,
        "iterations" : 10,
        "repetitions" : 320,
        "commit" : null,
        "vmRunConfiguration" : {
          "showStart" : false,
          "executeBeforeClassInMeasurement" : false,
          "redirectToTemp" : false,
          "redirectToNull" : true,
          "useKieker" : false
        },
        "javaVersion" : "1.8.0_312",
        "cpu" : "model name : Intel(R) Core(TM) i7-4770 CPU @ 3.40GHz",
        "memory" : "MemTotal: 16280696 kB",
        "date" : 1667855948648,
        "fulldata" : {
          "fileName" : null,
          "values" : [ {
            "startTime" : 1667855814870,
            "value" : 14220120415
          }, {
            "startTime" : 1667855829090,
            "value" : 13234190723
          }, {
            "startTime" : 1667855842325,
            "value" : 13197871882
          }, {
            "startTime" : 1667855855522,
            "value" : 13196610911
          }, {
            "startTime" : 1667855868719,
            "value" : 13393708874
          }, {
            "startTime" : 1667855882113,
            "value" : 13273473761
          }, {
            "startTime" : 1667855895386,
            "value" : 13271095628
          }, {
            "startTime" : 1667855908658,
            "value" : 13201023729
          }, {
            "startTime" : 1667855921859,
            "value" : 13296450533
          }, {
            "startTime" : 1667855935155,
            "value" : 13270912437
          } ]
        }
      } ]
    } ]
  } ]
}