{
  "clazz" : "org.apache.commons.fileupload.DiskFileItemSerializeTest",
  "methods" : [ {
    "method" : "testAboveThreshold",
    "datacollectorResults" : [ {
      "name" : "de.dagere.kopeme.datacollection.TimeDataCollectorNoGC",
      "chunks" : [ ],
      "results" : [ {
        "value" : 2.09174282873E10,
        "deviation" : 0.017161279080692312,
        "min" : 2.0362751095E10,
        "max" : 2.1721498775E10,
        "warmup" : 0,
        "iterations" : 10,
        "repetitions" : 200000,
        "commit" : null,
        "vmRunConfiguration" : {
          "showStart" : false,
          "executeBeforeClassInMeasurement" : false,
          "redirectToTemp" : false,
          "redirectToNull" : true,
          "useKieker" : false
        },
        "javaVersion" : "1.8.0_312",
        "cpu" : "model name : Intel(R) Core(TM) i7-4770 CPU @ 3.40GHz",
        "memory" : "MemTotal: 16280696 kB",
        "date" : 1667908318704,
        "fulldata" : {
          "fileName" : null,
          "values" : [ {
            "startTime" : 1667908109265,
            "value" : 21721498775
          }, {
            "startTime" : 1667908130987,
            "value" : 21087213289
          }, {
            "startTime" : 1667908152074,
            "value" : 20362751095
          }, {
            "startTime" : 1667908172437,
            "value" : 20618593667
          }, {
            "startTime" : 1667908193056,
            "value" : 20824111289
          }, {
            "startTime" : 1667908213880,
            "value" : 20938982981
          }, {
            "startTime" : 1667908234819,
            "value" : 20675178285
          }, {
            "startTime" : 1667908255494,
            "value" : 20985758699
          }, {
            "startTime" : 1667908276480,
            "value" : 21039372981
          }, {
            "startTime" : 1667908297519,
            "value" : 20920821812
          } ]
        }
      } ]
    } ]
  } ]
}