{
  "clazz" : "org.apache.commons.fileupload.util.mime.Base64DecoderTestCase",
  "methods" : [ {
    "method" : "nonBase64Bytes",
    "datacollectorResults" : [ {
      "name" : "de.dagere.kopeme.datacollection.TimeDataCollectorNoGC",
      "chunks" : [ ],
      "results" : [ {
        "value" : 1.6110065964E9,
        "deviation" : 0.03747884194959532,
        "min" : 1.579066332E9,
        "max" : 1.727298014E9,
        "warmup" : 0,
        "iterations" : 10,
        "repetitions" : 1000000,
        "commit" : null,
        "vmRunConfiguration" : {
          "showStart" : false,
          "executeBeforeClassInMeasurement" : false,
          "redirectToTemp" : false,
          "redirectToNull" : true,
          "useKieker" : false
        },
        "javaVersion" : "1.8.0_312",
        "cpu" : "model name : Intel(R) Core(TM) i7-4770 CPU @ 3.40GHz",
        "memory" : "MemTotal: 16280696 kB",
        "date" : 1667742962573,
        "fulldata" : {
          "fileName" : null,
          "values" : [ {
            "startTime" : 1667742946301,
            "value" : 1723454438
          }, {
            "startTime" : 1667742948025,
            "value" : 1727298014
          }, {
            "startTime" : 1667742949752,
            "value" : 1590005344
          }, {
            "startTime" : 1667742951342,
            "value" : 1580686378
          }, {
            "startTime" : 1667742952923,
            "value" : 1586358254
          }, {
            "startTime" : 1667742954509,
            "value" : 1579066332
          }, {
            "startTime" : 1667742956089,
            "value" : 1580999735
          }, {
            "startTime" : 1667742957670,
            "value" : 1581136576
          }, {
            "startTime" : 1667742959251,
            "value" : 1579166021
          }, {
            "startTime" : 1667742960830,
            "value" : 1581894872
          } ]
        }
      } ]
    } ]
  } ]
}